DarkSkyAPI/DSForecast.py
DarkSkyAPI/DS_logger.py
DarkSkyAPI/DarkSkyAPI.py
DarkSkyAPI/__init__.py
DarkSkyAPI/constants.py
darkskyapi_py-1.1.0.dist-info/METADATA
darkskyapi_py-1.1.0.dist-info/RECORD
darkskyapi_py-1.1.0.dist-info/WHEEL
darkskyapi_py-1.1.0.dist-info/top_level.txt
