Metadata-Version: 2.1
Name: darkskyapi-py
Version: 1.1.0
Summary: A simple Python API wrapper for the DarkSky weather API
Home-page: https://github.com/suplolx/Python-Weather-wrapper
Author: Hans Beijk
Author-email: hans.beijk1992@gmail.com
License: UNKNOWN
Platform: UNKNOWN
Classifier: Programming Language :: Python :: 3.6
Classifier: License :: OSI Approved :: MIT License
Classifier: Operating System :: OS Independent
Requires-Dist: requests
